zebra_analyzer_hu/__init__.py
zebra_analyzer_hu/analyzer.py
zebra_analyzer_hu/utils.py
zebra_analyzer_hu/zebra_files_hu/ZEBRA.D
zebra_analyzer_hu/zebra_files_hu/ZEBRA.DP
zebra_analyzer_hu/zebra_files_hu/ZEBRA.SAS
zebra_analyzer_hu/zebra_files_hu/ZEBRA.exe
zebra_analyzer_hu/zebra_files_hu/Zebra_Prop_Liq.txt
zebra_analyzer_hu/zebra_files_hu/Zebra_Prop_Sat.txt
zebra_analyzer_hu/zebra_files_hu/Zebra_Prop_out.txt
zebra_analyzer_hu/zebra_files_hu/zebra.in
zebra_analyzer_hu-1.2.dist-info/METADATA
zebra_analyzer_hu-1.2.dist-info/WHEEL
zebra_analyzer_hu-1.2.dist-info/entry_points.txt
zebra_analyzer_hu-1.2.dist-info/top_level.txt
zebra_analyzer_hu-1.2.dist-info/RECORD
